{
  "src/routes/+page.css": {
    "file": "_app/immutable/assets/_page-9784b081.css",
    "src": "src/routes/+page.css"
  },
  "_singletons-1eaa32f9.js": {
    "file": "_app/immutable/chunks/singletons-1eaa32f9.js",
    "imports": [
      "_index-d947be7e.js"
    ]
  },
  ".svelte-kit/generated/nodes/0.js": {
    "file": "_app/immutable/chunks/0-363c1efc.js",
    "src": ".svelte-kit/generated/nodes/0.js",
    "isDynamicEntry": true,
    "imports": [
      "node_modules/@sveltejs/kit/src/runtime/components/layout.svelte"
    ]
  },
  "_index-d947be7e.js": {
    "file": "_app/immutable/chunks/index-d947be7e.js",
    "imports": [
      "_index-1689419a.js"
    ]
  },
  ".svelte-kit/generated/nodes/1.js": {
    "file": "_app/immutable/chunks/1-4d84b927.js",
    "src": ".svelte-kit/generated/nodes/1.js",
    "isDynamicEntry": true,
    "imports": [
      "node_modules/@sveltejs/kit/src/runtime/components/error.svelte"
    ]
  },
  "__page-b14944b6.js": {
    "file": "_app/immutable/chunks/_page-b14944b6.js"
  },
  "node_modules/@sveltejs/kit/src/runtime/components/layout.svelte": {
    "file": "_app/immutable/components/layout.svelte-7589d8d8.js",
    "src": "node_modules/@sveltejs/kit/src/runtime/components/layout.svelte",
    "isEntry": true,
    "imports": [
      "_index-1689419a.js"
    ]
  },
  ".svelte-kit/generated/nodes/2.js": {
    "file": "_app/immutable/chunks/2-b1c41fe2.js",
    "src": ".svelte-kit/generated/nodes/2.js",
    "isDynamicEntry": true,
    "imports": [
      "__page-b14944b6.js",
      "src/routes/+page.svelte"
    ]
  },
  "node_modules/@sveltejs/kit/src/runtime/components/error.svelte": {
    "file": "_app/immutable/components/error.svelte-a6c34aa8.js",
    "src": "node_modules/@sveltejs/kit/src/runtime/components/error.svelte",
    "isEntry": true,
    "imports": [
      "_index-1689419a.js",
      "_singletons-1eaa32f9.js"
    ]
  },
  "src/routes/+page.js": {
    "file": "_app/immutable/modules/pages/_page.js-a01c9c9e.js",
    "src": "src/routes/+page.js",
    "isEntry": true,
    "imports": [
      "__page-b14944b6.js"
    ]
  },
  "_index-1689419a.js": {
    "file": "_app/immutable/chunks/index-1689419a.js"
  },
  "node_modules/@sveltejs/kit/src/runtime/client/start.js": {
    "file": "_app/immutable/start-67af6045.js",
    "src": "node_modules/@sveltejs/kit/src/runtime/client/start.js",
    "isEntry": true,
    "imports": [
      "_index-1689419a.js",
      "_singletons-1eaa32f9.js"
    ],
    "dynamicImports": [
      ".svelte-kit/generated/nodes/0.js",
      ".svelte-kit/generated/nodes/1.js",
      ".svelte-kit/generated/nodes/2.js"
    ]
  },
  "src/routes/+page.svelte": {
    "file": "_app/immutable/components/pages/_page.svelte-53c717fb.js",
    "src": "src/routes/+page.svelte",
    "isEntry": true,
    "imports": [
      "_index-1689419a.js",
      "_index-d947be7e.js"
    ],
    "css": [
      "_app/immutable/assets/_page-9784b081.css"
    ]
  }
}